tdcc/HtmlParser.py
tdcc/StructuredProductCrawler.py
tdcc/__init__.py
tdcc/translation.py
tdcc-0.0.2.dist-info/LICENSE
tdcc-0.0.2.dist-info/METADATA
tdcc-0.0.2.dist-info/WHEEL
tdcc-0.0.2.dist-info/top_level.txt
tdcc-0.0.2.dist-info/RECORD
