Metadata-Version: 2.1
Name: tdcc
Version: 0.0.2
Summary: A crawler for structured product information from TDCC (Taiwan).
Home-page: https://github.com/jn8029/tdcc
Author: jn8029
Author-email: warren.y.cheng@gmail.com
License: UNKNOWN
Platform: UNKNOWN
Classifier: Programming Language :: Python :: 3
Classifier: License :: OSI Approved :: MIT License
Classifier: Operating System :: OS Independent
Requires-Dist: bs4
Requires-Dist: requests
Requires-Dist: html5lib
